django_chip/__init__.py
django_chip/settings.py
django_chip/management/__init__.py
django_chip/management/utils.py
django_chip/management/commands/__init__.py
django_chip/management/commands/create_deploy.py
django_chip/management/commands/import_drf.py
django_chip/tmpl/deploy_template/requirements.txt.tmpl
django_chip/tmpl/deploy_template/supervisord.conf.tmpl
django_chip/tmpl/deploy_template/uwsgi.ini.tmpl
django_chip/tmpl/deploy_template/Docker/Dockerfile.tmpl
django_chip/tmpl/deploy_template/Docker/docker-compose.yml.tmpl
django_chip/tmpl/deploy_template/Docker/entrypoint.sh.tmpl
django_chip/tmpl/deploy_template/Docker/nginx.conf.tmpl
django_chip/tmpl/deploy_template/envs/.env.local.tmpl
django_chip/tmpl/deploy_template/envs/.env.prod.tmpl
django_chip/tmpl/drf_template/requirements.txt.tmpl
django_chip/tmpl/drf_template/settings.py.tmpl
django_chip/tmpl/drf_template/urls.py.tmpl
django_chip-0.0.4.dist-info/LICENSE
django_chip-0.0.4.dist-info/METADATA
django_chip-0.0.4.dist-info/WHEEL
django_chip-0.0.4.dist-info/top_level.txt
django_chip-0.0.4.dist-info/RECORD
